{
    "5": [
        {
            "start": 4,
            "end": 14,
            "refs": {
                "Ba'alei HaNefesh, Sha'ar HaPerishah": "בעלי הנפש, שער הפרישה"
            }
        }
    ],
    "6": [
        {
            "start": 5,
            "end": 6,
            "refs": {
                "Ba'alei HaNefesh, Sha'ar HaPerishah 1": "בעלי הנפש, שער הפרישה א׳"
            }
        }
    ],
    "14": [
        {
            "start": 99,
            "end": 110,
            "refs": {
                "Niddah 54b:10-57a:17": "נדה נ״ד ב:י׳-נ״ז א:י״ז"
            }
        },
        {
            "start": 567,
            "end": 571,
            "refs": {
                "Niddah 54b": "נדה נ״ד ב"
            }
        }
    ],
    "23": [
        {
            "start": 5,
            "end": 6,
            "refs": {
                "Sefer HaYashar 2": "ספר הישר ב׳"
            }
        }
    ],
    "24": [
        {
            "start": 394,
            "end": 405,
            "refs": {
                "Niddah 64b:5-73a:16": "נדה ס״ד ב:ה׳-ע״ג א:ט״ז"
            }
        }
    ],
    "25": [
        {
            "start": 77,
            "end": 88,
            "refs": {
                "Rashi on Niddah 63": "רש\"י על נדה ס״ג"
            }
        }
    ],
    "42": [
        {
            "start": 562,
            "end": 570,
            "refs": {
                "Niddah 36": "נדה ל״ו"
            }
        }
    ],
    "43": [
        {
            "start": 5,
            "end": 6,
            "refs": {
                "Mishnah Niddah 10": "משנה נדה י׳",
                "Niddah 10": "נדה י׳",
                "Niddah 64b:5-73a:16": "נדה ס״ד ב:ה׳-ע״ג א:ט״ז"
            }
        }
    ],
    "45": [
        {
            "start": 5,
            "end": 7,
            "refs": {
                "Niddah 11": "נדה י״א",
                "Halakhot Gedolot 11": "הלכות גדולות י״א"
            }
        }
    ],
    "46": [
        {
            "start": 532,
            "end": 546,
            "refs": {
                "Niddah 31b:18-39b:12": "נדה ל״א ב:י״ח-ל״ט ב:י״ב",
                "Jerusalem Talmud Niddah 4:1:1-7:1": "תלמוד ירושלמי נדה ד׳:א׳:א׳-ז׳:א׳"
            }
        }
    ],
    "51": [
        {
            "start": 728,
            "end": 737,
            "refs": {
                "Pesachim 87a:1-92b:3": "פסחים פ״ז א:א׳-צ״ב ב:ג׳",
                "Niddah 59b:1-64b:4": "נדה נ״ט ב:א׳-ס״ד ב:ד׳",
                "Jerusalem Talmud Pesachim 8:1:1-8:9": "תלמוד ירושלמי פסחים ח׳:א׳:א׳-ח׳:ט׳"
            }
        },
        {
            "start": 979,
            "end": 994,
            "refs": {
                "Niddah 31b:18-39b:12": "נדה ל״א ב:י״ח-ל״ט ב:י״ב",
                "Jerusalem Talmud Niddah 4:1:1-7:1": "תלמוד ירושלמי נדה ד׳:א׳:א׳-ז׳:א׳"
            }
        }
    ],
    "52": [
        {
            "start": 5,
            "end": 7,
            "refs": {
                "Niddah 14": "נדה י״ד"
            }
        }
    ],
    "53": [
        {
            "start": 622,
            "end": 637,
            "refs": {
                "Niddah 31b:18-39b:12": "נדה ל״א ב:י״ח-ל״ט ב:י״ב",
                "Jerusalem Talmud Niddah 4:1:1-7:1": "תלמוד ירושלמי נדה ד׳:א׳:א׳-ז׳:א׳"
            }
        }
    ],
    "54": [
        {
            "start": 5,
            "end": 7,
            "refs": {
                "Niddah 15": "נדה ט״ו"
            }
        }
    ],
    "56": [
        {
            "start": 5,
            "end": 7,
            "refs": {
                "Niddah 16": "נדה ט״ז"
            }
        }
    ],
    "64": [
        {
            "start": 1581,
            "end": 1592,
            "refs": {
                "Niddah 13a:1-21a:3": "נדה י״ג א:א׳-כ״א א:ג׳",
                "Jerusalem Talmud Niddah 2:1:1-7:9": "תלמוד ירושלמי נדה ב׳:א׳:א׳-ז׳:ט׳"
            }
        }
    ],
    "68": [
        {
            "start": 4,
            "end": 14,
            "refs": {
                "Ba'alei HaNefesh, Sha'ar HaKetamim": "בעלי הנפש, שער הכתמים"
            }
        }
    ],
    "69": [
        {
            "start": 5,
            "end": 6,
            "refs": {
                "Ba'alei HaNefesh, Sha'ar HaKetamim 1": "בעלי הנפש, שער הכתמים א׳"
            }
        }
    ],
    "70": [
        {
            "start": 299,
            "end": 316,
            "refs": {
                "Kiddushin 69a:12-82b:6": "קידושין ס״ט א:י״ב-פ״ב ב:ו׳",
                "Jerusalem Talmud Kiddushin 4:1:1-12:3": "תלמוד ירושלמי קידושין ד׳:א׳:א׳-י״ב:ג׳"
            }
        }
    ],
    "71": [
        {
            "start": 5,
            "end": 6,
            "refs": {
                "Mishnah Kiddushin 2": "משנה קידושין ב׳",
                "Kiddushin 2": "קידושין ב׳",
                "Kiddushin 41a:3-58b:11": "קידושין מ״א א:ג׳-נ״ח ב:י״א",
                "Kiddushin 69b": "קידושין ס״ט ב",
                "Jerusalem Talmud Kiddushin 2": "תלמוד ירושלמי קידושין ב׳",
                "Jerusalem Talmud Kiddushin 4:2": "תלמוד ירושלמי קידושין ד׳:ב׳"
            }
        }
    ],
    "73": [
        {
            "start": 5,
            "end": 6,
            "refs": {
                "Mishnah Kiddushin 3": "משנה קידושין ג׳",
                "Kiddushin 3": "קידושין ג׳",
                "Kiddushin 58b:12-69a:11": "קידושין נ״ח ב:י״ב-ס״ט א:י״א",
                "Jerusalem Talmud Kiddushin 2:3": "תלמוד ירושלמי קידושין ב׳:ג׳",
                "Jerusalem Talmud Kiddushin 3": "תלמוד ירושלמי קידושין ג׳",
                "Jerusalem Talmud Kiddushin 4:3": "תלמוד ירושלמי קידושין ד׳:ג׳"
            }
        }
    ],
    "75": [
        {
            "start": 4,
            "end": 22,
            "refs": {
                "Ba'alei HaNefesh, Sha'ar HaSefirah VeHabedikah": "בעלי הנפש, שער הספירה והבדיקה"
            }
        }
    ],
    "76": [
        {
            "start": 5,
            "end": 6,
            "refs": {
                "Ba'alei HaNefesh, Sha'ar HaSefirah VeHabedikah 1": "בעלי הנפש, שער הספירה והבדיקה א׳",
                "Tosefta Kiddushin (Lieberman) 1": "תוספתא קידושין (ליברמן) א׳",
                "Tosefta Kiddushin 1": "תוספתא קידושין א׳"
            }
        }
    ],
    "81": [
        {
            "start": 1016,
            "end": 1028,
            "refs": {
                "Mishnah Ketubot 1": "משנה כתובות א׳",
                "Ketubot 2a:1-15b:11": "כתובות ב׳ א:א׳-ט״ו ב:י״א"
            }
        }
    ],
    "82": [
        {
            "start": 5,
            "end": 6,
            "refs": {
                "Mishnah Ketubot 1:4": "משנה כתובות א׳:ד׳",
                "Mishnah Ketubot 4": "משנה כתובות ד׳",
                "Ketubot 4": "כתובות ד׳",
                "Ketubot 41b:11-54b:5": "כתובות מ״א ב:י״א-נ״ד ב:ה׳"
            }
        }
    ],
    "84": [
        {
            "start": 5,
            "end": 6,
            "refs": {
                "Mishnah Ketubot 4:5": "משנה כתובות ד׳:ה׳",
                "Mishnah Ketubot 5": "משנה כתובות ה׳",
                "Ketubot 5": "כתובות ה׳",
                "Ketubot 54b:6-65b:12": "כתובות נ״ד ב:ו׳-ס״ה ב:י״ב"
            }
        }
    ],
    "90": [
        {
            "start": 4,
            "end": 14,
            "refs": {
                "Ba'alei HaNefesh, Sha'ar HaTevilah": "בעלי הנפש, שער הטבילה"
            }
        }
    ],
    "91": [
        {
            "start": 5,
            "end": 6,
            "refs": {
                "Ba'alei HaNefesh, Sha'ar HaTevilah 1": "בעלי הנפש, שער הטבילה א׳"
            }
        }
    ],
    "100": [
        {
            "start": 0,
            "end": 9,
            "refs": {
                "Ba'alei HaNefesh, Sha'ar HaMayim": "בעלי הנפש, שער המים"
            }
        },
        {
            "start": 15,
            "end": 24,
            "refs": {
                "Ba'alei HaNefesh, Sha'ar HaMayim": "בעלי הנפש, שער המים"
            }
        }
    ],
    "105": [
        {
            "start": 5,
            "end": 6,
            "refs": {
                "Mishnah Yevamot 3": "משנה יבמות ג׳",
                "Mishnah Mikvaot 3": "משנה מקואות ג׳",
                "Yevamot 3": "יבמות ג׳",
                "Yevamot 26a:15-35a:11": "יבמות כ״ו א:ט״ו-ל״ה א:י״א"
            }
        }
    ],
    "106": [
        {
            "start": 332,
            "end": 342,
            "refs": {
                "Bava Kamma 62b:7-83a:12": "בבא קמא ס״ב ב:ז׳-פ״ג א:י״ב",
                "Jerusalem Talmud Bava Kamma 7:1:1-7:6": "תלמוד ירושלמי בבא קמא ז׳:א׳:א׳-ז׳:ו׳"
            }
        }
    ],
    "109": [
        {
            "start": 4,
            "end": 14,
            "refs": {
                "Ba'alei HaNefesh, Sha'ar HaKedushah": "בעלי הנפש, שער הקדושה"
            }
        }
    ],
    "110": [
        {
            "start": 3,
            "end": 20,
            "refs": {
                "Ba'alei HaNefesh, Sha'ar HaKedushah": "בעלי הנפש, שער הקדושה"
            }
        }
    ]
}