[
  {
    "line_index_1": 7,
    "heRef_2": "ספר עבודה, הלכות כלי המקדש והעובדין בו, פרק ב, ד",
    "path_2": "משנה תורה, הלכות כלי המקדש והעובדין בו.txt",
    "line_index_2": 27,
    "Conection Type": "commentary"
  },
  {
    "line_index_1": 11,
    "heRef_2": "ספר עבודה, הלכות מעילה, פרק ו, א",
    "path_2": "משנה תורה, הלכות מעילה.txt",
    "line_index_2": 78,
    "Conection Type": "commentary"
  },
  {
    "line_index_1": 16,
    "heRef_2": "ספר משפטים, הלכות שכירות, פרק יא, ו",
    "path_2": "משנה תורה, הלכות שכירות.txt",
    "line_index_2": 114,
    "Conection Type": "commentary"
  },
  {
    "line_index_1": 21,
    "heRef_2": "ספר שופטים, הלכות ממרים, פרק ד, ב",
    "path_2": "משנה תורה, הלכות ממרים.txt",
    "line_index_2": 30,
    "Conection Type": "commentary"
  },
  {
    "line_index_1": 23,
    "heRef_2": "ספר שופטים, הלכות ממרים, פרק ד, ג",
    "path_2": "משנה תורה, הלכות ממרים.txt",
    "line_index_2": 31,
    "Conection Type": "commentary"
  }
]