[
  {
    "line_index_1": 7,
    "heRef_2": "ספר מדע, הלכות יסודי התורה, פרק ה, ה",
    "path_2": "משנה תורה, הלכות יסודי התורה.txt",
    "line_index_2": 60,
    "Conection Type": "commentary"
  },
  {
    "line_index_1": 12,
    "heRef_2": "ספר זמנים, הלכות חמץ ומצה, פרק א, ה",
    "path_2": "משנה תורה, הלכות חמץ ומצה.txt",
    "line_index_2": 8,
    "Conection Type": "commentary"
  },
  {
    "line_index_1": 14,
    "heRef_2": "ספר זמנים, הלכות חמץ ומצה, פרק א, ט",
    "path_2": "משנה תורה, הלכות חמץ ומצה.txt",
    "line_index_2": 12,
    "Conection Type": "commentary"
  },
  {
    "line_index_1": 19,
    "heRef_2": "ספר נשים, הלכות אישות, פרק ז, יא",
    "path_2": "משנה תורה, הלכות אישות.txt",
    "line_index_2": 148,
    "Conection Type": "commentary"
  },
  {
    "line_index_1": 23,
    "heRef_2": "ספר נשים, הלכות גירושין, פרק י, יח",
    "path_2": "משנה תורה, הלכות גירושין.txt",
    "line_index_2": 259,
    "Conection Type": "commentary"
  },
  {
    "line_index_1": 26,
    "heRef_2": "ספר נשים, הלכות גירושין, פרק יג, א",
    "path_2": "משנה תורה, הלכות גירושין.txt",
    "line_index_2": 320,
    "Conection Type": "commentary"
  },
  {
    "line_index_1": 31,
    "heRef_2": "ספר קדושה, הלכות איסורי ביאה, פרק יג, יד",
    "path_2": "משנה תורה, הלכות איסורי ביאה.txt",
    "line_index_2": 303,
    "Conection Type": "commentary"
  },
  {
    "line_index_1": 35,
    "heRef_2": "ספר קדושה, הלכות שחיטה, פרק ג, יח",
    "path_2": "משנה תורה, הלכות שחיטה.txt",
    "line_index_2": 74,
    "Conection Type": "commentary"
  },
  {
    "line_index_1": 40,
    "heRef_2": "ספר זרעים, הלכות כלאים, פרק י, כז",
    "path_2": "משנה תורה, הלכות כלאים.txt",
    "line_index_2": 189,
    "Conection Type": "commentary"
  },
  {
    "line_index_1": 45,
    "heRef_2": "ספר טהרה, הלכות טומאת מת, פרק ט, יב",
    "path_2": "משנה תורה, הלכות טומאת מת.txt",
    "line_index_2": 124,
    "Conection Type": "commentary"
  },
  {
    "line_index_1": 49,
    "heRef_2": "ספר טהרה, הלכות פרה אדומה, פרק י, א",
    "path_2": "משנה תורה, הלכות פרה אדומה.txt",
    "line_index_2": 118,
    "Conection Type": "commentary"
  },
  {
    "line_index_1": 54,
    "heRef_2": "ספר נזיקין, הלכות רוצח ושמירת נפש, פרק ב, ב",
    "path_2": "משנה תורה, הלכות רוצח ושמירת נפש.txt",
    "line_index_2": 22,
    "Conection Type": "commentary"
  },
  {
    "line_index_1": 59,
    "heRef_2": "ספר קניין, הלכות עבדים, פרק ז, ה",
    "path_2": "משנה תורה, הלכות עבדים.txt",
    "line_index_2": 92,
    "Conection Type": "commentary"
  },
  {
    "line_index_1": 64,
    "heRef_2": "ספר שופטים, הלכות סנהדרין והעונשין המסורין להם, פרק טז, ו",
    "path_2": "משנה תורה, הלכות סנהדרין והעונשין המסורין להם.txt",
    "line_index_2": 176,
    "Conection Type": "commentary"
  },
  {
    "line_index_1": 68,
    "heRef_2": "ספר שופטים, הלכות ממרים, פרק ה, י",
    "path_2": "משנה תורה, הלכות ממרים.txt",
    "line_index_2": 42,
    "Conection Type": "commentary"
  }
]